src/__init__.py
src/main.py
src/knext/__init__.py
src/knext/call.py
src/knext/convert.py
src/knext/genes.py
src/knext/mixed.py
tests/__init__.py
tests/test_get_kgml.py
tests/test_graph.py
knext-1.2.1.dist-info/LICENSE
knext-1.2.1.dist-info/METADATA
knext-1.2.1.dist-info/WHEEL
knext-1.2.1.dist-info/entry_points.txt
knext-1.2.1.dist-info/top_level.txt
knext-1.2.1.dist-info/RECORD
