Metadata-Version: 2.1
Name: knext
Version: 1.2.1
Summary: Kyoto Encylopedia of Genes and Genomes Markup Language File parser and converter
Home-page: https://github.com/everest-castaneda/knext
Author: Everest Uriel Castaneda
Author-email: Everest_Castaneda1@baylor.edu
Project-URL: Bug Tracker, https://github.com/everest-castaneda/knext/issues
Classifier: Programming Language :: Python :: 3
Classifier: License :: OSI Approved :: MIT License
Classifier: Operating System :: OS Independent
License-File: LICENSE
Requires-Dist: networkx
Requires-Dist: Click
Requires-Dist: pandas
Requires-Dist: typer
Requires-Dist: requests
Requires-Dist: pathlib
Requires-Dist: pytest
